griffonner/__init__.py
griffonner/cli.py
griffonner/config.py
griffonner/core.py
griffonner/frontmatter.py
griffonner/griffe_wrapper.py
griffonner/templates.py
griffonner/watcher.py
griffonner/plugins/__init__.py
griffonner/plugins/base.py
griffonner/plugins/manager.py
griffonner/plugins/protocols.py
griffonner-0.3.5.dist-info/licenses/LICENSE
griffonner-0.3.5.dist-info/METADATA
griffonner-0.3.5.dist-info/WHEEL
griffonner-0.3.5.dist-info/entry_points.txt
griffonner-0.3.5.dist-info/top_level.txt
griffonner-0.3.5.dist-info/RECORD
