Metadata-Version: 2.4
Name: griffonner
Version: 0.3.5
Summary: A templating tool for Griffe.
Author-email: Will Langdale <willdon@gmail.com>
License: MIT License
Requires-Python: <3.14,>=3.9
License-File: LICENSE
Requires-Dist: griffe>=1.12.1
Requires-Dist: typer>=0.16.1
Requires-Dist: jinja2>=3.1.0
Requires-Dist: pyyaml>=6.0
Requires-Dist: pydantic>=2.0.0
Requires-Dist: watchdog>=3.0.0
Requires-Dist: tomli>=1.2.0
Dynamic: license-file
